{
    "variants": 
    {
        "active=false,facing=north": { "model": "hutosmod:fusion_furnace" },
        "active=false,facing=east": { "model": "hutosmod:fusion_furnace", "y": 90 },
        "active=false,facing=south": { "model": "hutosmod:fusion_furnace", "y": 180 },
        "active=false,facing=west": { "model": "hutosmod:fusion_furnace", "y": 270 },
        "active=true,facing=north": { "model": "hutosmod:lit_fusion_furnace" },
        "active=true,facing=east": { "model": "hutosmod:lit_fusion_furnace", "y": 90 },
        "active=true,facing=south": { "model": "hutosmod:lit_fusion_furnace", "y": 180 },
        "active=true,facing=west": { "model": "hutosmod:lit_fusion_furnace", "y":270  }
    }
}